nvbenjo/__init__.py
nvbenjo/benchmark.py
nvbenjo/cfg.py
nvbenjo/cli.py
nvbenjo/onnx_utils.py
nvbenjo/plot.py
nvbenjo/plugin.py
nvbenjo/system_info.py
nvbenjo/torch_utils.py
nvbenjo/utils.py
nvbenjo/conf/bert.yaml
nvbenjo/conf/complex_example.yaml
nvbenjo/conf/default.yaml
nvbenjo/conf/example.yaml
nvbenjo/conf/huggingface.yaml
nvbenjo/conf/onnx.yaml
nvbenjo/conf/onnxsilero.yaml
nvbenjo/conf/small.yaml
nvbenjo/conf/torchvision.yaml
nvbenjo/conf/hydra/help/nvbenjo_app_help.yaml
nvbenjo-0.0.2.dist-info/licenses/LICENSE
nvbenjo-0.0.2.dist-info/METADATA
nvbenjo-0.0.2.dist-info/WHEEL
nvbenjo-0.0.2.dist-info/entry_points.txt
nvbenjo-0.0.2.dist-info/top_level.txt
nvbenjo-0.0.2.dist-info/RECORD
