Metadata-Version: 2.4
Name: nvbenjo
Version: 0.0.2
Summary: Nvbenjo is a utility for benchmarking inference of deep learning models on NVIDIA GPUs.
Author: lukas_jkl
Requires-Python: <3.15,>=3.10
License-File: LICENSE
Requires-Dist: torchvision
Requires-Dist: torchaudio
Requires-Dist: nvitop
Requires-Dist: psutil
Requires-Dist: py-cpuinfo
Requires-Dist: hydra-core
Requires-Dist: hydra_colorlog
Requires-Dist: nvidia-ml-py
Requires-Dist: pandas
Requires-Dist: seaborn
Requires-Dist: rich
Provides-Extra: onnx-cpu
Requires-Dist: onnx>=1.14.0; extra == "onnx-cpu"
Requires-Dist: onnxruntime>=1.15.0; extra == "onnx-cpu"
Provides-Extra: onnx-gpu
Requires-Dist: onnx>=1.14.0; extra == "onnx-gpu"
Requires-Dist: onnxruntime-gpu>=1.15.0; extra == "onnx-gpu"
Dynamic: license-file
